<?xml version="1.0" encoding="UTF-8"?>
<schemalist>
  <schema id="com.github.efdos.mupengui.ui" path="/com/github/efdos/mupengui/ui/" gettext-domain="mupengui">
    <key name="rom-dir" type="s">
      <default>""</default>
      <summary>Saved rom directory</summary>
      <description>Saved rom directory to be automatically opened.</description>
    </key>
    <key name="dark-mode" type="b">
      <default>false</default>
      <summary>Use dark theme</summary>
      <description>Enable/disable prefer-dark-theme gtk setting</description>
    </key>
  </schema>
</schemalist>
